{
  "last_run": "2026-04-20T16:41:49.779263+00:00",
  "targets": {
    "VOO": {
      "last_daily": {
        "ts": "2026-04-20T16:41:49.176662+00:00",
        "trading_date": "2026-04-20",
        "score": 0,
        "max_score": 7,
        "level": "none",
        "triggered_ids": []
      }
    },
    "QQQ": {
      "last_daily": {
        "ts": "2026-04-20T16:41:49.779220+00:00",
        "trading_date": "2026-04-20",
        "score": 0,
        "max_score": 7,
        "level": "none",
        "triggered_ids": []
      }
    }
  },
  "cached_indicators": {
    "VOO": {
      "rsi_14": 72.85995290608307,
      "ma50_deviation": 0.05143123420294357,
      "mtd_drawdown": 0.0,
      "from_52w_high": -0.0032066570521011406,
      "_candle_cached_at": "2026-04-20T03:27:49.341940+00:00"
    },
    "QQQ": {
      "rsi_14": 74.43709135361695,
      "ma50_deviation": 0.07764415449726719,
      "mtd_drawdown": 0.0,
      "from_52w_high": -0.001769268329326923,
      "_candle_cached_at": "2026-04-20T03:27:49.627162+00:00"
    }
  },
  "data_health": {
    "finnhub": "ok",
    "yfinance": null,
    "fred": null,
    "cnn_fgi": "ok",
    "vix": "ok (yfinance)",
    "candles_VOO": "ok (refreshed)",
    "candles_QQQ": "ok (refreshed)"
  }
}