{
  "last_run": "2026-05-13T19:03:06.181453+00:00",
  "targets": {
    "VOO": {
      "last_daily": {
        "ts": "2026-04-29T01:14:57.709559+00:00",
        "trading_date": "2026-04-28",
        "score": 0,
        "max_score": 7,
        "level": "none",
        "triggered_ids": []
      }
    },
    "QQQ": {
      "last_daily": {
        "ts": "2026-04-29T01:14:58.238658+00:00",
        "trading_date": "2026-04-28",
        "score": 0,
        "max_score": 7,
        "level": "none",
        "triggered_ids": []
      }
    }
  },
  "cached_indicators": {
    "VOO": {
      "rsi_14": 75.77600834869159,
      "ma50_deviation": 0.07811343833326052,
      "mtd_drawdown": 0.0,
      "from_52w_high": -0.0022611488457171657,
      "_candle_cached_at": "2026-05-12T19:04:24.409003+00:00"
    },
    "QQQ": {
      "rsi_14": 83.21397107077982,
      "ma50_deviation": 0.1448722354128834,
      "mtd_drawdown": 0.0,
      "from_52w_high": -0.001819293272039948,
      "_candle_cached_at": "2026-05-12T19:04:24.671526+00:00"
    }
  },
  "data_health": {
    "finnhub": "ok",
    "yfinance": null,
    "fred": null,
    "cnn_fgi": "ok",
    "vix": "ok (yfinance)",
    "candles_VOO": "ok (refreshed)",
    "candles_QQQ": "ok (refreshed)"
  }
}